regex2dfa.cpython-38-x86_64-linux-gnu.so
regex2dfa2-0.0.1.dist-info/METADATA
regex2dfa2-0.0.1.dist-info/WHEEL
regex2dfa2-0.0.1.dist-info/top_level.txt
regex2dfa2-0.0.1.dist-info/RECORD
